MANIFEST.in
README.md
setup.cfg
setup.py
pageshot/__init__.py
pageshot.egg-info/PKG-INFO
pageshot.egg-info/SOURCES.txt
pageshot.egg-info/dependency_links.txt
pageshot.egg-info/requires.txt
pageshot.egg-info/top_level.txt