Metadata-Version: 1.0
Name: pageshot
Version: 0.0.1
Summary: UNKNOWN
Home-page: https://github.com/sketchytechky/pageshot
Author: Boris Lau
Author-email: boris@techie.im
License: UNKNOWN
Platform: UNKNOWN
